beatstarsdownloader/__init__.py
beatstarsdownloader/__main__.py
beatstarsdownloader/beatstarsdownloader.py
beatstarsdownloader/config.py
beatstarsdownloader/logger.py
beatstarsdownloader/url_helpers.py
beatstarsdownloader-0.2.1.dist-info/LICENSE
beatstarsdownloader-0.2.1.dist-info/METADATA
beatstarsdownloader-0.2.1.dist-info/WHEEL
beatstarsdownloader-0.2.1.dist-info/entry_points.txt
beatstarsdownloader-0.2.1.dist-info/RECORD
