Metadata-Version: 2.3
Name: beatstarsdownloader
Version: 0.2.1
Summary: Tool for downloading all BeatStars tracks from an artist to mp3
License: MIT
Keywords: beatstars,downloader,mp3,music
Author: Tim Morriss
Author-email: tim.morriss@gmail.com
Requires-Python: >=3.9
Classifier: License :: OSI Approved :: MIT License
Classifier: Programming Language :: Python :: 3
Classifier: Programming Language :: Python :: 3.9
Classifier: Programming Language :: Python :: 3.10
Classifier: Programming Language :: Python :: 3.11
Classifier: Programming Language :: Python :: 3.12
Classifier: Programming Language :: Python :: 3.13
Requires-Dist: beautifulsoup4 (>=4.12.0,<5.0.0)
Requires-Dist: filetype (>=1.2.0,<2.0.0)
Requires-Dist: halo (>=0.0.31)
Requires-Dist: mutagen (>=1.47.0,<2.0.0)
Requires-Dist: pillow (>=10.0.0)
Requires-Dist: pydub (>=0.25.1)
Requires-Dist: questionary (>=2.0.0,<3.0.0)
Requires-Dist: requests (>=2.28.0,<3.0.0)
Requires-Dist: rich (>=13.0.0)
Requires-Dist: selenium (>=4.15.0,<5.0.0)
Requires-Dist: simple-chalk (>=0.1.0)
Requires-Dist: tqdm (>=4.65.0,<5.0.0)
Requires-Dist: validators (>=0.20.0)
